{
  "project_info": {
    "project_number": "876934993940",
    "project_id": "swapapp-44a7d",
    "storage_bucket": "swapapp-44a7d.firebasestorage.app"
  },
  "client": [
    {
      "client_info": {
        "mobilesdk_app_id": "1:876934993940:android:7021dde3a19463f14cef01",
        "android_client_info": {
          "package_name": "com.example.swapapp"
        }
      },
      "oauth_client": [],
      "api_key": [
        {
          "current_key": "AIzaSyCb-gzq9wvDxZpNW6Myq1yYmW8uqwDhoI8"
        }
      ],
      "services": {
        "appinvite_service": {
          "other_platform_oauth_client": []
        }
      }
    }
  ],
  "configuration_version": "1"
}